browseapi/__init__.py
browseapi/client.py
browseapi/containers.py
browseapi/exceptions.py
browseapi-0.12.2.dist-info/LICENSE.txt
browseapi-0.12.2.dist-info/METADATA
browseapi-0.12.2.dist-info/WHEEL
browseapi-0.12.2.dist-info/top_level.txt
browseapi-0.12.2.dist-info/RECORD
