Metadata-Version: 1.1
Name: browseapi
Version: 0.12.2
Summary: eBay Browse API Python client
Home-page: https://github.com/AverHLV/browseapi
Author: Andrii Matiiash
Author-email: andmati743@gmail.com
License: MIT
Download-URL: https://github.com/AverHLV/browseapi/archive/0.12.2.tar.gz
Keywords: ASYNC,BROWSE API,CLIENT
Platform: UNKNOWN
Classifier: Development Status :: 3 - Alpha
Classifier: Intended Audience :: Developers
Classifier: Topic :: Software Development :: Libraries
Classifier: License :: OSI Approved :: MIT License
Classifier: Programming Language :: Python :: 3.5
Classifier: Programming Language :: Python :: 3.6
Classifier: Programming Language :: Python :: 3.7
